[
  {
    "name": "Олексій",
    "altegioId": 5595441
  },
  {
    "name": "Вікторія Дума",
    "altegioId": 12157291,
    "dbId": "68147d12e7d12ddfd45178ab",
    "crmId": 20803713
  },
  {
    "name": "Микола",
    "altegioId": 12166066
  },
  {
    "name": "Service",
    "altegioId": 12166672
  },
  {
    "name": "Кривяк Алла",
    "altegioId": 12166856
  },
  {
    "name": "Галько Марія",
    "altegioId": 12166857
  },
  {
    "name": "Білінська Соломія",
    "altegioId": 12166866,
    "dbId": "68272759e7b4b50792ecc0ef",
    "crmId": 11005380
  },
  {
    "name": "Тонкопій Юлія",
    "altegioId": 12166868,
    "crmId": 11005326
  },
  {
    "name": "Футь Зоряна",
    "altegioId": 12166869,
    "crmId": 11005330
  },
  {
    "name": "Кубрак Вероніка",
    "altegioId": 12166876,
    "dbId": "679343b5f3e59f80e370b7d3",
    "crmId": 11005370
  },
  {
    "name": "Гордійчук Поліна",
    "altegioId": 12166877,
    "dbId": "671645220c6de992a6359f39",
    "crmId": 11005374
  },
  {
    "name": "Дейнека Юлія",
    "altegioId": 12166883,
    "crmId": 11005756
  },
  {
    "name": "Коваль Лілія",
    "altegioId": 12166889,
    "crmId": 11005712
  },
  {
    "name": "Ольга Булавка",
    "altegioId": 12171727,
    "crmId": 14268111
  },
  {
    "name": "Кирило Жеребілов",
    "altegioId": 12174538
  },
  {
    "name": "Мар'яна Стуй",
    "altegioId": 12174728,
    "dbId": "671645220c6de992a6359f59",
    "crmId": 14270273
  },
  {
    "name": "Вікторія Дмитренко",
    "altegioId": 12176914,
    "dbId": "6793449ef3e59f80e370b7e2",
    "crmId": 11853834
  },
  {
    "name": "Іван Джавала",
    "altegioId": 12182436
  },
  {
    "name": "Юлія Ходовицька",
    "altegioId": 12185723,
    "crmId": 13897795
  },
  {
    "name": "Дар'я Баштавенко",
    "altegioId": 12186103,
    "crmId": 13897771
  },
  {
    "name": "Володимир Усов",
    "altegioId": 12188780,
    "crmId": 13897719
  },
  {
    "name": "Богдан Швец",
    "altegioId": 12189974
  },
  {
    "name": "Тетяна Вишневська",
    "altegioId": 12191640
  },
  {
    "name": "Helen Egbo",
    "altegioId": 12193544,
    "crmId": 14140671
  },
  {
    "name": "Олександра Цюх",
    "altegioId": 12193864,
    "dbId": "671645220c6de992a6359f64"
  },
  {
    "name": "Іванка Савчак",
    "altegioId": 12204098
  },
  {
    "name": "Мар'яна Мещенюк",
    "altegioId": 12211165,
    "crmId": 14986541
  },
  {
    "name": "Христина Красногурська",
    "altegioId": 12410870,
    "dbId": "671645220c6de992a6359f72",
    "crmId": 16049761
  },
  {
    "name": "Шутка Елеонора",
    "altegioId": 12475213
  },
  {
    "name": "Софія Горобйовська",
    "altegioId": 12575741,
    "crmId": 15856863
  },
  {
    "name": "Дар'я Мойсеєнко",
    "altegioId": 12601032,
    "dbId": "671645220c6de992a6359f48",
    "crmId": 16048285
  },
  {
    "name": "Марія Тимчишин",
    "altegioId": 12604233
  },
  {
    "name": "Лимаренко Катерина",
    "altegioId": 12606068
  },
  {
    "name": "Віталій Дзядзик",
    "altegioId": 12606426
  },
  {
    "name": "Любов Пена",
    "altegioId": 12606427,
    "crmId": 15093453
  },
  {
    "name": "Руслан Зверюк",
    "altegioId": 12607917
  },
  {
    "name": "Sales",
    "altegioId": 12608018
  },
  {
    "name": "Тетяна Фурман",
    "altegioId": 12622414,
    "crmId": 18499049
  },
  {
    "name": "Надія Самоніна",
    "altegioId": 12625647,
    "dbId": "671645220c6de992a6359f57"
  },
  {
    "name": "Олександра Драпак",
    "altegioId": 12625648
  },
  {
    "name": "Карина Моруга",
    "altegioId": 12625736,
    "dbId": "67bc6dde456747a249753f5c"
  },
  {
    "name": "Діана Боднар",
    "altegioId": 12627128,
    "dbId": "671645220c6de992a6359f33",
    "crmId": 18600417
  },
  {
    "name": "Михайло Гайворонський",
    "altegioId": 12627465,
    "crmId": 18678135
  },
  {
    "name": "Каріна Головко",
    "altegioId": 12628255,
    "dbId": "671645220c6de992a6359f38",
    "crmId": 13106077
  },
  {
    "name": "Олексій Алхазов",
    "altegioId": 12629280,
    "dbId": "671645220c6de992a6359f71",
    "crmId": 18360593
  },
  {
    "name": "Hulkin Kirill",
    "altegioId": 12629568
  },
  {
    "name": "Yevhen Oniehin",
    "altegioId": 12629569
  },
  {
    "name": "Вікторія Івачевська",
    "altegioId": 12630166,
    "dbId": "67c984fb4601f62b2addcc45",
    "crmId": 18810835
  },
  {
    "name": "Роман Кобрин",
    "altegioId": 12630170,
    "dbId": "671645220c6de992a6359f7d",
    "crmId": 17401097
  },
  {
    "name": "Андріана Жук",
    "altegioId": 12635938,
    "crmId": 18824811
  },
  {
    "name": "Ольга Долока",
    "altegioId": 12652209,
    "dbId": "671645220c6de992a6359f7a",
    "crmId": 17788997
  },
  {
    "name": "Rituraj",
    "altegioId": 12662818
  },
  {
    "name": "Цвігун Наталія",
    "altegioId": 12664335,
    "dbId": "671645220c6de992a6359f62",
    "crmId": 15437887
  },
  {
    "name": "Новіцька Діана",
    "altegioId": 12693017,
    "dbId": "67402e730933d7096601a844",
    "crmId": 16291063
  },
  {
    "name": "Ірина Кривуля",
    "altegioId": 12702882,
    "dbId": "679342b3f3e59f80e370b718"
  },
  {
    "name": "Марина Романенко",
    "altegioId": 12703295,
    "dbId": "671645220c6de992a6359f83",
    "crmId": 18207913
  },
  {
    "name": "Іванна Петрикович",
    "altegioId": 12704439,
    "crmId": 19045369
  },
  {
    "name": "Анастасія",
    "altegioId": 12705563
  },
  {
    "name": "Федір Міщенко",
    "altegioId": 12706529,
    "dbId": "671645220c6de992a6359f47",
    "crmId": 16021743
  },
  {
    "name": "Анна Гудз",
    "altegioId": 12706530,
    "crmId": 19220753
  },
  {
    "name": "Софія Павлик",
    "altegioId": 12708154,
    "crmId": 15623657
  },
  {
    "name": "Тетяна Петрів",
    "altegioId": 12708547,
    "dbId": "671645220c6de992a6359f52",
    "crmId": 15184511
  },
  {
    "name": "Андріяна Наконечна",
    "altegioId": 12708911,
    "dbId": "671645220c6de992a6359f82",
    "crmId": 18690481
  },
  {
    "name": "Анна Гаманюк",
    "altegioId": 12709525,
    "dbId": "671645220c6de992a6359f36",
    "crmId": 13113179
  },
  {
    "name": "Марина Стефанюк",
    "altegioId": 12714854,
    "dbId": "67934333f3e59f80e370b721",
    "crmId": 19413733
  },
  {
    "name": "Аліна Черниш",
    "altegioId": 12715709,
    "crmId": 19421331
  },
  {
    "name": "Maria Poliszczuk",
    "altegioId": 12719747
  },
  {
    "name": "Погорельська Таїсія",
    "altegioId": 12720740,
    "crmId": 19480123
  },
  {
    "name": "Maximilian",
    "altegioId": 12721645
  },
  {
    "name": "Ангеліна Шульгач DE A1-A2",
    "altegioId": 12722958,
    "crmId": 19630335
  },
  {
    "name": "Богдан Павлюк",
    "altegioId": 12723716
  },
  {
    "name": "Ярослав Гуцуляк (ЛИШЕ ВЕБІНАРИ)",
    "altegioId": 12724270,
    "dbId": "672e8993850395b97527988d",
    "crmId": 19608581
  },
  {
    "name": "Софія Чернявська DE",
    "altegioId": 12726271,
    "dbId": "67afa94e6e9fa2ffd7359d18",
    "crmId": 20666385
  },
  {
    "name": "Ірина Лавірко DE",
    "altegioId": 12726275,
    "crmId": 20314033
  },
  {
    "name": "Віталія Вільчик",
    "altegioId": 12729432,
    "crmId": 19794173
  },
  {
    "name": "Ілля (ТЕСТУВАННЯ)",
    "altegioId": 12729879
  },
  {
    "name": "Лілія Борис DE",
    "altegioId": 12734347,
    "crmId": 19564777
  },
  {
    "name": "Каріна Янчева N",
    "altegioId": 12740111,
    "dbId": "671645220c6de992a6359f68",
    "crmId": 15198983
  },
  {
    "name": "Мар&#039;яна Євуш (ЛИШЕ ВЕБІНАРИ)",
    "altegioId": 12745166
  },
  {
    "name": "Ксенія Прохира",
    "altegioId": 12746563,
    "dbId": "67afa9dc6e9fa2ffd7359d1e",
    "crmId": 20365603
  },
  {
    "name": "Ірина Марченко DE N",
    "altegioId": 12747153,
    "crmId": 20314033
  },
  {
    "name": "Сніжана Грициняк DE N",
    "altegioId": 12747183,
    "crmId": 17105395
  },
  {
    "name": "Іванкіна Сніжана DE N",
    "altegioId": 12747399,
    "crmId": 17105395
  },
  {
    "name": "Олександра",
    "altegioId": 12748215
  },
  {
    "name": "Пюро Дарія N",
    "altegioId": 12749543
  },
  {
    "name": "Тетяна Колесник",
    "altegioId": 12749978
  },
  {
    "name": "Ірина Остапчук DE N",
    "altegioId": 12750305,
    "crmId": 20314033
  },
  {
    "name": "Ірина Задворна",
    "altegioId": 12750306,
    "dbId": "67c0c179dea5d3460d9eddd0",
    "crmId": 20509813
  },
  {
    "name": "Анастасія Косянчук",
    "altegioId": 12750978,
    "crmId": 20425285
  },
  {
    "name": "Ірина Руцька",
    "altegioId": 12751660,
    "crmId": 20544351
  },
  {
    "name": "Лілія Барановська N",
    "altegioId": 12751717,
    "dbId": "671645220c6de992a6359f2e",
    "crmId": 15656057
  },
  {
    "name": "Марта Кунта N",
    "altegioId": 12752922,
    "crmId": 20561519
  },
  {
    "name": "Софія Бойко",
    "altegioId": 12757325,
    "dbId": "67d989dff1a01367ffcd43da",
    "crmId": 20666385
  },
  {
    "name": "Eduard Shyts",
    "altegioId": 12757662
  },
  {
    "name": "Олеся Томашівська",
    "altegioId": 12758879,
    "crmId": 20694611
  },
  {
    "name": "Тетяна Лелях DE N",
    "altegioId": 12763441,
    "dbId": "67e54aca019938e01e6ccaa3",
    "crmId": 20701509
  },
  {
    "name": "Наталія Когут",
    "altegioId": 12764097,
    "crmId": 20710515
  },
  {
    "name": "Анастасія Фіногеєва N",
    "altegioId": 12764381,
    "dbId": "671645220c6de992a6359f60",
    "crmId": 15098543
  },
  {
    "name": "Вероніка Костенко DE N",
    "altegioId": 12776604,
    "dbId": "680f3487eaccd3ac989b44e3",
    "crmId": 21126239
  },
  {
    "name": "Світлана Кулінська DE N",
    "altegioId": 12777342
  },
  {
    "name": "Анастасія Найда",
    "altegioId": 12777343,
    "dbId": "68278efe0932c0fca0aa63ce",
    "crmId": 21138751
  },
  {
    "name": "Луб&#039;яницька Катерина",
    "altegioId": 12777682
  },
  {
    "name": "Олійник Анастасія DE N",
    "altegioId": 12778346,
    "crmId": 21138751
  },
  {
    "name": "Косенко Ігор DE N",
    "altegioId": 12779226
  },
  {
    "name": "Шаламова Євгенія DE N",
    "altegioId": 12780371,
    "crmId": 21217275
  },
  {
    "name": "Кравчук Оксана DE N",
    "altegioId": 12782879,
    "crmId": 18696787
  }
]